dktoeasysqlite3/__init__.py
dktoeasysqlite3/_add_db.py
dktoeasysqlite3/_execute.py
dktoeasysqlite3/_get_datas.py
dktoeasysqlite3/_insert_data.py
dktoeasysqlite3/_request_db.py
dktoeasysqlite3/global_var_storage.py
dktoeasysqlite3/structbdd.py
dktoeasysqlite3-1.0.2.dist-info/LICENCE.txt
dktoeasysqlite3-1.0.2.dist-info/METADATA
dktoeasysqlite3-1.0.2.dist-info/WHEEL
dktoeasysqlite3-1.0.2.dist-info/top_level.txt
dktoeasysqlite3-1.0.2.dist-info/RECORD
