Metadata-Version: 2.1
Name: dktoeasysqlite3
Version: 1.0.2
Summary: Some commands to call sqlite3 db easyly
Home-page: https://discord-catho.frama.io/easysqlite3
Author: Pierre
License: APGL
Project-URL: Source Code, https://framagit.org/discord-catho/easysqlite3
Keywords: sqlite,sqlite3
Requires-Python: <4,>=3.9
License-File: LICENCE.txt
Provides-Extra: doc
Requires-Dist: sphinx (==6.2.1) ; extra == 'doc'
Requires-Dist: sphinx-rtd-theme (==1.2.1) ; extra == 'doc'
Requires-Dist: myst-parser (==1.0.0) ; extra == 'doc'
